AlgorithmicGameTheoryLectureNotesCornellCs6840/README.md
AlgorithmicGameTheoryLectureNotesCornellCs6840/__init__.py
AlgorithmicGameTheoryLectureNotesCornellCs6840/__main__.py
AlgorithmicGameTheoryLectureNotesCornellCs6840/file.pdf
AlgorithmicGameTheoryLectureNotesCornellCs6840/index.html
algorithmic_game_theory_lecture_notes_cornell_cs6840-2024.3.1.0.dist-info/METADATA
algorithmic_game_theory_lecture_notes_cornell_cs6840-2024.3.1.0.dist-info/WHEEL
algorithmic_game_theory_lecture_notes_cornell_cs6840-2024.3.1.0.dist-info/entry_points.txt
algorithmic_game_theory_lecture_notes_cornell_cs6840-2024.3.1.0.dist-info/top_level.txt
algorithmic_game_theory_lecture_notes_cornell_cs6840-2024.3.1.0.dist-info/RECORD
